Metadata-Version: 2.1
Name: elixir-lsp
Version: 1.5.1
Summary: Multi-Language Server WebSocket proxy for Elixir Notebook/Lab server
Author: ciusji
Author-email: bqjimaster@gmail.com
License: BSD-3-Clause
Project-URL: Bug Tracker, https://github.com/ElixirNote/elixirlsp/issues
Project-URL: Documentation, https://github.com/ElixirNote/elixirlsp
Project-URL: Source Code, https://github.com/ElixirNote/elixirlsp
Keywords: Interactive,Language Server,LSP
Classifier: Framework :: Jupyter
Classifier: Intended Audience :: Developers
Classifier: Intended Audience :: Information Technology
Classifier: License :: OSI Approved :: BSD License
Classifier: Programming Language :: Python
Requires-Python: >=3.7
License-File: LICENSE
